README.md
setup.py
orange/__init__.py
orange/__version__.py
orange/config.py
orange/coroutine.py
orange/debug.py
orange/deploy.py
orange/hclient.py
orange/htutil.py
orange/mail.py
orange/markdown.py
orange/pysetup.py
orange/pyver.py
orange/regkey.py
orange/sqlite.py
orange/version.py
orange/xlsx.py
orange/pykit/pysetup.py
orange/data/mongo.plist
orange/data/mongo.yaml
orange/pykit/__init__.py
orange/pykit/pysetup.py
orange/shell/__init__.py
orange/shell/path.py
orange/shell/shell.py
orange/tools/__init__.py
orange/tools/fkgfw.py
orange/tools/gclone.py
orange/tools/ggcs.py
orange/tools/init.py
orange/tools/math.py
orange/tools/mongodb.py
orange/tools/plist.py
orange/tools/pypkgs.py
orange/tools/pyupgrade.py
orange/tools/sysinit.py
orange/utils/__init__.py
orange/utils/checksum.py
orange/utils/click.py
orange/utils/datetime.py
orange/utils/pinyin.py
orange/utils/pyDes.py
orange/utils/regex.py
orange_kit.egg-info/PKG-INFO
orange_kit.egg-info/SOURCES.txt
orange_kit.egg-info/dependency_links.txt
orange_kit.egg-info/entry_points.txt
orange_kit.egg-info/requires.txt
orange_kit.egg-info/top_level.txt
scripts/pytest.py