Metadata-Version: 1.0
Name: orange-kit
Version: 0.1.7a30
Summary: orange
Home-page: https://github.com/huangtao-sh/orange.git
Author: huangtao
Author-email: huangtao.sh@icloud.com
License: GPL
Platform: any
